ruten_crawler/HtmlParser.py
ruten_crawler/ProductCrawler.py
ruten_crawler/__init__.py
rutencrawler/HtmlParser.py
rutencrawler/ProductCrawler.py
rutencrawler/__init__.py
ruten_crawler-0.0.6.dist-info/LICENSE
ruten_crawler-0.0.6.dist-info/METADATA
ruten_crawler-0.0.6.dist-info/WHEEL
ruten_crawler-0.0.6.dist-info/top_level.txt
ruten_crawler-0.0.6.dist-info/RECORD
