Metadata-Version: 2.1
Name: ruten-crawler
Version: 0.0.6
Summary: A crawler for product information of sellers on Ruten.
Home-page: https://github.com/jn8029/ruten_crawler
Author: jn8029
Author-email: warren.y.cheng@gmail.com
License: UNKNOWN
Platform: UNKNOWN
Classifier: Programming Language :: Python :: 3
Classifier: License :: OSI Approved :: MIT License
Classifier: Operating System :: OS Independent
Requires-Dist: bs4
Requires-Dist: requests
